messenger2/__init__.py
messenger2/config.py
messenger2/server.ini
messenger2/server_start.py
messenger2/common/__init__.py
messenger2/common/decorators.py
messenger2/common/descriptors.py
messenger2/common/metaclasses.py
messenger2/common/security/__init__.py
messenger2/common/security/decript_data.py
messenger2/common/security/encript_data.py
messenger2/common/security/hash_password.py
messenger2/common/security/keys.py
messenger2/databases/__init__.py
messenger2/databases/database.py
messenger2/logs/__init__.py
messenger2/logs/client_logs/__init__.py
messenger2/logs/log_configs/__init__.py
messenger2/logs/log_configs/client_log_config.py
messenger2/logs/log_configs/server_log_config.py
messenger2/logs/server_logs/__init__.py
messenger2/protocols/BaseProtocol.py
messenger2/protocols/JIM.py
messenger2/protocols/__init__.py
messenger2/server/__init__.py
messenger2/server/core.py
messenger2/server/gui/__init__.py
messenger2/server/gui/alert_window.py
messenger2/server/gui/config_window.py
messenger2/server/gui/history_window.py
messenger2/server/gui/info_window.py
messenger2/server/gui/register_window.py
messenger2/server/gui/server_main.py
messenger2/server/gui/ui/__init__.py
messenger2/server/gui/ui/register_user.ui
python_messenger_server-0.0.5.dist-info/METADATA
python_messenger_server-0.0.5.dist-info/WHEEL
python_messenger_server-0.0.5.dist-info/top_level.txt
python_messenger_server-0.0.5.dist-info/RECORD
